pyxplora_api/__init__.py
pyxplora_api/const.py
pyxplora_api/const_version.py
pyxplora_api/exception_classes.py
pyxplora_api/gql_handler.py
pyxplora_api/gql_handler_async.py
pyxplora_api/gql_mutations.py
pyxplora_api/gql_queries.py
pyxplora_api/graphql_client.py
pyxplora_api/handler_gql.py
pyxplora_api/model.py
pyxplora_api/pyxplora.py
pyxplora_api/pyxplora_api.py
pyxplora_api/pyxplora_api_async.py
pyxplora_api/status.py
pyxplora_api-2.12.9.dist-info/LICENSE
pyxplora_api-2.12.9.dist-info/METADATA
pyxplora_api-2.12.9.dist-info/WHEEL
pyxplora_api-2.12.9.dist-info/top_level.txt
pyxplora_api-2.12.9.dist-info/RECORD
