Metadata-Version: 2.1
Name: pyxplora-api
Version: 2.12.9
Summary: Python Xplora® Api
Home-page: https://github.com/Ludy87/pyxplora_api
Author: Ludy87
Author-email: android@astra-g.org
License: MIT
Project-URL: Bug Tracker, https://github.com/Ludy87/pyxplora_api/issues
Keywords: api xplora watch
Platform: UNKNOWN
Classifier: Development Status :: 5 - Production/Stable
Classifier: Programming Language :: Python
Classifier: Programming Language :: Python :: 3.9
Classifier: Programming Language :: Python :: 3.10
Classifier: Programming Language :: Python :: 3.11
Classifier: License :: OSI Approved :: MIT License
Classifier: Operating System :: OS Independent
Classifier: Intended Audience :: Developers
Classifier: Topic :: Software Development
Classifier: Topic :: Utilities
Classifier: Topic :: Home Automation
Classifier: Topic :: Software Development :: Libraries :: Python Modules
Requires-Python: >=3.9
License-File: LICENSE
Requires-Dist: aiohttp >=3.9
Requires-Dist: dataclasses-json >=0.6
Requires-Dist: geopy ==2.4.1
Requires-Dist: python-graphql-client >=0.4
Requires-Dist: requests >=2
